Metadata-Version: 1.0
Name: pysubmodule
Version: 0.1.1
Summary: painless submodule manager
Home-page: https://github.com/williamfzc/pysubmodule
Author: williamfzc
Author-email: fengzc@vip.qq.com
License: UNKNOWN
Platform: UNKNOWN
